date_extract/__init__.py
date_extract/date_extract.py
src/__init__.py
tests/__init__.py
tests/test_date_extract.py
date_extract-0.0.4.dist-info/LICENSE
date_extract-0.0.4.dist-info/METADATA
date_extract-0.0.4.dist-info/WHEEL
date_extract-0.0.4.dist-info/top_level.txt
date_extract-0.0.4.dist-info/RECORD
