Metadata-Version: 2.1
Name: date_extract
Version: 0.0.4
Summary: Detect and extract dates
Home-page: https://github.com/e-e/date_extractor
Author: Eric Ellingson
Author-email: Eric Ellingson <god@eric.wtf>
Project-URL: Homepage, https://github.com/e-e/date_extractor
Project-URL: Issues, https://github.com/e-e/date_extractor/issues
Classifier: Programming Language :: Python :: 3
Classifier: License :: OSI Approved :: MIT License
Classifier: Operating System :: OS Independent
Requires-Python: >=3.12
License-File: LICENSE
